pinky/__init__.py
pinky/exceptions.py
pinky/canonicalization/__init__.py
pinky/canonicalization/disambiguate.py
pinky/canonicalization/equiv.py
pinky/canonicalization/primes.py
pinky/canonicalization/smiles.py
pinky/canonicalization/tokens.py
pinky/canonicalization/traverse.py
pinky/fingerprints/__init__.py
pinky/fingerprints/ecfp.py
pinky/mol/__init__.py
pinky/mol/atom.py
pinky/mol/atypes.py
pinky/mol/bond.py
pinky/mol/chirality.py
pinky/mol/idgen.py
pinky/mol/molecule.py
pinky/perception/__init__.py
pinky/perception/aromaticity.py
pinky/perception/cycle.py
pinky/perception/figueras.py
pinky/smiles/__init__.py
pinky/smiles/builder.py
pinky/smiles/handler.py
pinky/smiles/parser.py
pinky-0.0.3.dist-info/AUTHORS
pinky-0.0.3.dist-info/LICENSE
pinky-0.0.3.dist-info/METADATA
pinky-0.0.3.dist-info/WHEEL
pinky-0.0.3.dist-info/top_level.txt
pinky-0.0.3.dist-info/RECORD
