Metadata-Version: 2.1
Name: pinky
Version: 0.0.3
Summary: pinky - molecular fingerprint library
Home-page: https://github.com/ubccr/pinky
Author: Andrew E. Bruno
Author-email: aebruno2@buffalo.edu
License: BSD
Platform: UNKNOWN
Classifier: Development Status :: 3 - Alpha
Classifier: Environment :: Console
Classifier: Intended Audience :: Developers
Classifier: Intended Audience :: Science/Research
Classifier: Programming Language :: Python
Classifier: License :: OSI Approved :: BSD License
Classifier: Topic :: Scientific/Engineering :: Bio-Informatics
Requires-Dist: bitarray
